{"columns":[{"kind":"Default","name":"confidence","num_defaults":0,"num_rows":13},{"kind":"Default","name":"modelversion","num_defaults":0,"num_rows":13},{"kind":"Default","name":"pricetarget","num_defaults":10,"num_rows":13},{"kind":"Default","name":"signal","num_defaults":0,"num_rows":13},{"kind":"Default","name":"strength","num_defaults":0,"num_rows":13},{"kind":"Default","name":"symbol","num_defaults":0,"num_rows":13},{"kind":"Default","name":"timestamp","num_defaults":0,"num_rows":13}],"version":0}